{"_path":"/dir/galaxy_maids","_dir":"dir","_draft":false,"_partial":false,"_locale":"","title":"Galaxy Maids","description":"","body":{"type":"root","children":[{"type":"element","tag":"h1","props":{"id":"galaxy-maids"},"children":[{"type":"text","value":"Galaxy Maids"}]},{"type":"element","tag":"h2","props":{"id":"business-information"},"children":[{"type":"text","value":"Business Information"}]},{"type":"element","tag":"ul","props":{},"children":[{"type":"element","tag":"li","props":{},"children":[{"type":"text","value":"Category: 4.8(73) · House cleaning service"}]},{"type":"element","tag":"li","props":{},"children":[{"type":"text","value":"Description: Galaxy Maids4.8(73) · House cleaning service3+ years in business · New York, NYClosed ⋅ Opens 9 AM Wed · (212) 899-5067"}]}]},{"type":"element","tag":"h2","props":{"id":"contact-information"},"children":[{"type":"text","value":"Contact Information"}]},{"type":"element","tag":"ul","props":{},"children":[{"type":"element","tag":"li","props":{},"children":[{"type":"text","value":"Address: 3+ years in business · New York, NY"}]},{"type":"element","tag":"li","props":{},"children":[{"type":"text","value":"Phone: Closed ⋅ Opens 9 AM Wed · (212) 899-5067"}]}]},{"type":"element","tag":"h2","props":{"id":"ratings-reviews"},"children":[{"type":"text","value":"Ratings & Reviews"}]},{"type":"element","tag":"ul","props":{},"children":[{"type":"element","tag":"li","props":{},"children":[{"type":"text","value":"Rating: 4.8"}]},{"type":"element","tag":"li","props":{},"children":[{"type":"text","value":"Number of Reviews: (73)"}]}]},{"type":"element","tag":"hr","props":{},"children":[]},{"type":"element","tag":"p","props":{},"children":[{"type":"text","value":"Generated: 1/15/2025, 5:25:30 AM"}]}],"toc":{"title":"","searchDepth":2,"depth":2,"links":[{"id":"business-information","depth":2,"text":"Business Information"},{"id":"contact-information","depth":2,"text":"Contact Information"},{"id":"ratings-reviews","depth":2,"text":"Ratings & Reviews"}]}},"_type":"markdown","_id":"content:dir:Galaxy_Maids.md","_source":"content","_file":"dir/Galaxy_Maids.md","_stem":"dir/Galaxy_Maids","_extension":"md","sitemap":{"loc":"/dir/galaxy_maids"}}